repolish/__init__.py
repolish/builder.py
repolish/cli.py
repolish/config.py
repolish/cookiecutter.py
repolish/debug_cli.py
repolish/processors.py
repolish/py.typed
repolish/utils.py
repolish/version.py
repolish/loader/__init__.py
repolish/loader/_log.py
repolish/loader/anchors.py
repolish/loader/context.py
repolish/loader/create_only.py
repolish/loader/deletes.py
repolish/loader/mappings.py
repolish/loader/module.py
repolish/loader/orchestrator.py
repolish/loader/types.py
repolish/loader/validation.py
repolish-0.5.0.dist-info/METADATA
repolish-0.5.0.dist-info/WHEEL
repolish-0.5.0.dist-info/entry_points.txt
repolish-0.5.0.dist-info/licenses/LICENSE
repolish-0.5.0.dist-info/RECORD
