Metadata-Version: 2.4
Name: repolish
Version: 0.5.0
Summary: Maintain consistency across repositories
Author: hotdog-werx
License-Expression: MIT
License-File: LICENSE
Requires-Python: >=3.11
Requires-Dist: cookiecutter>=2.6.0
Requires-Dist: hotlog>=0.1.1
Requires-Dist: pydantic>=2.0.0
